ImplementingALanguageWithLlvm/README.md
ImplementingALanguageWithLlvm/__init__.py
ImplementingALanguageWithLlvm/__main__.py
ImplementingALanguageWithLlvm/file.epub
ImplementingALanguageWithLlvm/index.html
ImplementingALanguageWithLlvm/css/__init__.py
ImplementingALanguageWithLlvm/css/annotations.css
ImplementingALanguageWithLlvm/css/main.css
ImplementingALanguageWithLlvm/css/normalize.css
ImplementingALanguageWithLlvm/css/popup.css
ImplementingALanguageWithLlvm/font/__init__.py
ImplementingALanguageWithLlvm/font/fontello.eot
ImplementingALanguageWithLlvm/font/fontello.svg
ImplementingALanguageWithLlvm/font/fontello.ttf
ImplementingALanguageWithLlvm/font/fontello.woff
ImplementingALanguageWithLlvm/img/__init__.py
ImplementingALanguageWithLlvm/img/annotator-glyph-sprite.png
ImplementingALanguageWithLlvm/img/annotator-icon-sprite.png
ImplementingALanguageWithLlvm/img/apple-touch-icon.png
ImplementingALanguageWithLlvm/img/cancelfullscreen.png
ImplementingALanguageWithLlvm/img/close.png
ImplementingALanguageWithLlvm/img/fullscreen.png
ImplementingALanguageWithLlvm/img/loader.gif
ImplementingALanguageWithLlvm/img/menu-icon.png
ImplementingALanguageWithLlvm/img/save.png
ImplementingALanguageWithLlvm/img/saved.png
ImplementingALanguageWithLlvm/img/settings-s.png
ImplementingALanguageWithLlvm/img/settings.png
ImplementingALanguageWithLlvm/img/star.png
ImplementingALanguageWithLlvm/js/__init__.py
ImplementingALanguageWithLlvm/js/epub.js
ImplementingALanguageWithLlvm/js/epub.min.js
ImplementingALanguageWithLlvm/js/epub.min.map
ImplementingALanguageWithLlvm/js/hooks.min.js
ImplementingALanguageWithLlvm/js/hooks.min.map
ImplementingALanguageWithLlvm/js/reader.js
ImplementingALanguageWithLlvm/js/reader.js.map
ImplementingALanguageWithLlvm/js/reader.min.js
ImplementingALanguageWithLlvm/js/reader.min.map
ImplementingALanguageWithLlvm/js/hooks/__init__.py
ImplementingALanguageWithLlvm/js/hooks/extensions/__init__.py
ImplementingALanguageWithLlvm/js/hooks/extensions/highlight.js
implementing_a_language_with_llvm-2024.3.2.0.dist-info/METADATA
implementing_a_language_with_llvm-2024.3.2.0.dist-info/WHEEL
implementing_a_language_with_llvm-2024.3.2.0.dist-info/entry_points.txt
implementing_a_language_with_llvm-2024.3.2.0.dist-info/top_level.txt
implementing_a_language_with_llvm-2024.3.2.0.dist-info/RECORD
